{
    "name": "Beatriz Duque",
    "jobTitle": "Lcda. Mercadeo y Publicidad",
    "bio":  "Hola, soy Beatriz Duque, mercadólogo con +8 años de experiencia en el área de marketing digital.\nAyudo a potenciar los negocios de marcas a través de marketing de contenidos, redes sociales, benchmarking, estrategia y publicidad online.",
    "avatar": "img/bduque.jpeg",
    "contact": {
        "telephone":  {
            "text": "(+58) 4145823713",
            "link": "https://wa.me/584145823713?text=Hola, me interesa trabajar contigo"
        },
        "email": "juhariduque@gmail.com",
        "location": "Caracas, Venezuela"
    },
    "socialNetworks": [
        {
            "icon": "fab fa-instagram",
            "url": "https://www.instagram.com/_beatrizduque",
            "username": "_beatrizduque"
        }
    ],
    "features": {
        "title": "Mis Servicios",
        "description": "Ofrecemos una variedad de servicios para ayudarte a alcanzar tus metas.",
        "services": [
            {
                "icon": "fas fa-rocket",
                "style": "primary",
                "title": "Branding y Estrategia",
                "text": "Te ayudamos a definir tu identidad de marca y a crear una estrategia para llegar a tu público objetivo."
            },
            {
                "icon": "fas fa-tools",
                "style": "success",
                "title": "Gestión de Proyectos",
                "text": "Gestionamos tus proyectos de principio a fin, asegurando que se entreguen a tiempo y dentro del presupuesto."
            },
            {
                "icon": "fas fa-pencil",
                "style": "warning",
                "title": "Creación de Contenido",
                "text": "Creamos contenido de alta calidad que atrae a tu audiencia e impulsa resultados."
            }
        ]
    },
    "recentWork": {
        "title": "Trabajos Realizados",
        "type": "video",
        "items": [
            {
                "url": "video/W150340.mp4",
                "thumbnail": "video/thumb_W150340.png",
                "poster": "video/poster_W150340.jpg",
                "title": "MERCURY",
                "caption": "Creación de contenido"
            },
            {
                "url": "video/W150444.mp4",
                "thumbnail": "video/thumbnail2.png",
                "title": "Product photography",
                "caption": "Digital, Photography"
            },
            {
                "url": "video/W150721.mp4",
                "thumbnail": "video/thumbnail3.png",
                "title": "Product photography",
                "caption": "Digital, Photography"
            },
            {
                "url": "video/W150722.mp4",
                "thumbnail": "video/thumbnail1.png",
                "title": "Tour and potrait",
                "caption": "Digital, Photography"
            },
            {
                "url": "video/W151103.mp4",
                "thumbnail": "video/thumbnail2.png",
                "title": "Classical photography",
                "caption": "Digital, Photography"
            },
            {
                "url": "video/W151209.mp4",
                "thumbnail": "video/thumbnail3.png",
                "title": "Urban photography",
                "caption": "Digital, Photography"
            },
            {
                "url": "video/W151408.mp4",
                "thumbnail": "video/thumbnail1.png",
                "title": "Classical photography",
                "caption": "Digital, Photography"
            }
        ]
    },
    "portfolio": {
        "title": "Portafolio",
        "images": [
            {
                "url": "img/portfolio-img1.png",
                "title": "Natural site",
                "layout": "bx-1"
            },
            {
                "url": "img/portfolio-img2.png",
                "title": "Vacation special photography",
                "layout": "bx-2"
            },
            {
                "url": "img/portfolio-img3.png",
                "title": "Product photography",
                "layout": "bx-3"
            },
            {
                "url": "img/portfolio-img6.png",
                "title": "Historical place shots",
                "layout": "bx-4"
            },
            {
                "url": "img/portfolio-img4.png",
                "title": "Urban photography",
                "layout": "bx-4"
            },
            {
                "url": "img/portfolio-img5.png",
                "title": "Outdoors photography",
                "layout": "bx-4"
            },
            {
                "url": "img/portfolio-img7.png",
                "title": "Outdoors photography",
                "layout": "bx-1"
            },
            {
                "url": "img/portfolio-img8.png",
                "title": "Outdoors photography",
                "layout": "bx-2"
            }
        ]
    }
}